VDBpy/__init__.py
VDBpy/indexing.py
VDBpy/query.py
VDBpy/similarity.py
VDBpy-0.1.4.dist-info/METADATA
VDBpy-0.1.4.dist-info/WHEEL
VDBpy-0.1.4.dist-info/top_level.txt
VDBpy-0.1.4.dist-info/RECORD
